python_calendar/__init__.py
tests/__init__.py
tests/test_init.py
python_calendar-0.0.2.dist-info/LICENSE
python_calendar-0.0.2.dist-info/METADATA
python_calendar-0.0.2.dist-info/WHEEL
python_calendar-0.0.2.dist-info/top_level.txt
python_calendar-0.0.2.dist-info/RECORD
