Metadata-Version: 2.1
Name: python-calendar
Version: 0.0.2
Home-page: https://github.com/anthonykgross/python-calendar
Author: Anthony K GROSS
Author-email: anthony.k.gross@gmail.com
Classifier: Programming Language :: Python :: 3
Classifier: License :: OSI Approved :: MIT License
Classifier: Operating System :: OS Independent
Requires-Python: >=3.8
License-File: LICENSE
Requires-Dist: python-dateutil
